<annotation><folder>G:/Work/multi-objective/shipdataset/VOC2007_ship/VOC2007</folder>
<filename>000005.jpeg</filename>
<path>G:/Work/multi-objective/shipdataset/VOC2007_ship/VOC2007/JPEGImages/000005.jpeg</path>
<source>
<database>Unknown</database>
</source>
<size>
<width>1280</width>
<height>720</height>
<depth>3</depth>
</size>
<segmented>0</segmented>
<object>
<direction>3</direction>
<name>CommonShip</name>
<pose>Unspecified</pose>
<truncated>0</truncated>
<difficult>0</difficult>
<bndbox>
<xmin>802</xmin>
<ymin>425</ymin>
<xmax>1140</xmax>
<ymax>596</ymax>
</bndbox>
</object>
<object>
<direction>4</direction>
<name>CommonShip</name>
<pose>Unspecified</pose>
<truncated>0</truncated>
<difficult>0</difficult>
<bndbox>
<xmin>109</xmin>
<ymin>410</ymin>
<xmax>399</xmax>
<ymax>561</ymax>
</bndbox>
</object>
<object>
<direction>7</direction>
<name>CommonShip</name>
<pose>Unspecified</pose>
<truncated>0</truncated>
<difficult>0</difficult>
<bndbox>
<xmin>934</xmin>
<ymin>311</ymin>
<xmax>1000</xmax>
<ymax>373</ymax>
</bndbox>
</object>
<object>
<direction>6</direction>
<name>CommonShip</name>
<pose>Unspecified</pose>
<truncated>0</truncated>
<difficult>0</difficult>
<bndbox>
<xmin>837</xmin>
<ymin>332</ymin>
<xmax>871</xmax>
<ymax>359</ymax>
</bndbox>
</object>
</annotation>